{"data": [{"id": 23545031, "name": "Mermail Abyssalacia", "type": "Link Monster", "card_sets": [{"set_name": "Danger in the Outer Depths (5649)", "set_code": "Dang-00", "set_rarity": "04ul"}]}, {"id": 82685480, "name": "Rage of Kairyu-Shin", "type": "Spell Card", "card_sets": [{"set_name": "Danger in the Outer Depths (5649)", "set_code": "Dang-01", "set_rarity": "04ul"}]}, {"id": 88307361, "name": "Superancient Deepsea King Coelacanth", "type": "Effect Monster", "card_sets": [{"set_name": "Danger in the Outer Depths (5649)", "set_code": "Dang-02", "set_rarity": "04ul"}]}, {"id": 44883830, "name": "Des Croaking", "type": "Spell Card", "card_sets": [{"set_name": "Danger in the Outer Depths (5649)", "set_code": "Dang-03", "set_rarity": "04ul"}]}, {"id": 21044178, "name": "Abyss Dweller", "type": "XYZ Monster", "card_sets": [{"set_name": "Danger in the Outer Depths (5649)", "set_code": "Dang-04", "set_rarity": "04ul"}]}, {"id": 74371660, "name": "Mermail Abyssgaios", "type": "XYZ Monster", "card_sets": [{"set_name": "Danger in the Outer Depths (5649)", "set_code": "Dang-05", "set_rarity": "04ul"}]}, {"id": 44223284, "name": "Abyssal Kingshark", "type": "Effect Monster", "card_sets": [{"set_name": "Danger in the Outer Depths (5649)", "set_code": "Dang-06", "set_rarity": "04ul"}]}, {"id": 49221191, "name": "Number C32: Shark Drake Veiss", "type": "XYZ Monster", "card_sets": [{"set_name": "Danger in the Outer Depths (5649)", "set_code": "Dang-07", "set_rarity": "04ul"}]}, {"id": 61258740, "name": "Sea Lord's Amulet", "type": "Spell Card", "card_sets": [{"set_name": "Danger in the Outer Depths (5649)", "set_code": "Dang-08", "set_rarity": "04ul"}]}, {"id": 53582587, "name": "Torrential Tribute", "type": "Trap Card", "card_sets": [{"set_name": "Danger in the Outer Depths (5649)", "set_code": "Dang-09", "set_rarity": "04ul"}]}]}