{"data": [{"id": 50277355, "name": "Cross-Sheep", "type": "Link Monster", "card_sets": [{"set_name": "Miscellaneous Rituals (5201)", "set_code": "Misc-00", "set_rarity": "04ul"}]}, {"id": 57970721, "name": "Drytron Asterism", "type": "Spell Card", "card_sets": [{"set_name": "Miscellaneous Rituals (5201)", "set_code": "Misc-01", "set_rarity": "04ul"}]}, {"id": 60375194, "name": "Vendread Daybreak", "type": "Trap Card", "card_sets": [{"set_name": "Miscellaneous Rituals (5201)", "set_code": "Misc-02", "set_rarity": "04ul"}]}, {"id": 83326048, "name": "Dimensional Barrier", "type": "Trap Card", "card_sets": [{"set_name": "Miscellaneous Rituals (5201)", "set_code": "Misc-03", "set_rarity": "04ul"}]}, {"id": 11877465, "name": "Evigishki Mind Augus", "type": "Ritual Effect Monster", "card_sets": [{"set_name": "Miscellaneous Rituals (5201)", "set_code": "Misc-04", "set_rarity": "04ul"}]}, {"id": 49202162, "name": "Black Luster Soldier - Soldier of Chaos", "type": "Link Monster", "card_sets": [{"set_name": "Miscellaneous Rituals (5201)", "set_code": "Misc-05", "set_rarity": "04ul"}]}, {"id": 84211599, "name": "Pot of Prosperity", "type": "Spell Card", "card_sets": [{"set_name": "Miscellaneous Rituals (5201)", "set_code": "Misc-06", "set_rarity": "04ul"}]}, {"id": 65589010, "name": "Dogmatika Nation", "type": "Spell Card", "card_sets": [{"set_name": "Miscellaneous Rituals (5201)", "set_code": "Misc-07", "set_rarity": "04ul"}]}, {"id": 49238328, "name": "Pot of Extravagance", "type": "Spell Card", "card_sets": [{"set_name": "Miscellaneous Rituals (5201)", "set_code": "Misc-08", "set_rarity": "04ul"}]}, {"id": 87054946, "name": "Nephthys, the Sacred Flame", "type": "Link Monster", "card_sets": [{"set_name": "Miscellaneous Rituals (5201)", "set_code": "Misc-09", "set_rarity": "04ul"}]}]}