{"data": [{"id": 30802207, "name": "Exosister Carpedivem", "type": "Spell Card", "card_sets": [{"set_name": "Mythic Constellation (5018)", "set_code": "Myth-00", "set_rarity": "03su"}]}, {"id": 18205590, "name": "Satellarknight Skybridge", "type": "Spell Card", "card_sets": [{"set_name": "Mythic Constellation (5018)", "set_code": "Myth-01", "set_rarity": "03su"}]}, {"id": 3292267, "name": "Hieratic Sky Dragon Overlord of Heliopolis", "type": "XYZ Monster", "card_sets": [{"set_name": "Mythic Constellation (5018)", "set_code": "Myth-02", "set_rarity": "03su"}]}, {"id": 67173574, "name": "Number C102: Archfiend Seraph", "type": "XYZ Monster", "card_sets": [{"set_name": "Mythic Constellation (5018)", "set_code": "Myth-03", "set_rarity": "03su"}]}, {"id": 64014615, "name": "Pot of Acquisitiveness", "type": "Spell Card", "card_sets": [{"set_name": "Mythic Constellation (5018)", "set_code": "Myth-04", "set_rarity": "03su"}]}, {"id": 68396121, "name": "Number C107: Neo Galaxy-Eyes Tachyon Dragon", "type": "XYZ Monster", "card_sets": [{"set_name": "Mythic Constellation (5018)", "set_code": "Myth-05", "set_rarity": "03su"}]}, {"id": 8165596, "name": "Number 90: Galaxy-Eyes Photon Lord", "type": "XYZ Monster", "card_sets": [{"set_name": "Mythic Constellation (5018)", "set_code": "Myth-06", "set_rarity": "03su"}]}, {"id": 47805931, "name": "Number 20: Giga-Brilliant", "type": "XYZ Monster", "card_sets": [{"set_name": "Mythic Constellation (5018)", "set_code": "Myth-07", "set_rarity": "03su"}]}, {"id": 55758589, "name": "Photon Wyvern", "type": "Effect Monster", "card_sets": [{"set_name": "Mythic Constellation (5018)", "set_code": "Myth-08", "set_rarity": "03su"}]}, {"id": 58820923, "name": "Number 95: Galaxy-Eyes Dark Matter Dragon", "type": "XYZ Monster", "card_sets": [{"set_name": "Mythic Constellation (5018)", "set_code": "Myth-09", "set_rarity": "03su"}]}, {"id": 37115973, "name": "Numeral Hunter", "type": "Effect Monster", "card_sets": [{"set_name": "Mythic Constellation (5018)", "set_code": "Myth-010", "set_rarity": "03su"}]}, {"id": 63956833, "name": "Galaxy Trance", "type": "Spell Card", "card_sets": [{"set_name": "Mythic Constellation (5018)", "set_code": "Myth-011", "set_rarity": "03su"}]}, {"id": 58374502, "name": "Starry Knight Blast", "type": "Trap Card", "card_sets": [{"set_name": "Mythic Constellation (5018)", "set_code": "Myth-012", "set_rarity": "03su"}]}, {"id": 90156158, "name": "Constellar Star Cradle", "type": "Spell Card", "card_sets": [{"set_name": "Mythic Constellation (5018)", "set_code": "Myth-013", "set_rarity": "03su"}]}, {"id": 15381421, "name": "Starliege Seyfert", "type": "Effect Monster", "card_sets": [{"set_name": "Mythic Constellation (5018)", "set_code": "Myth-014", "set_rarity": "03su"}]}]}